README
setup.py
lib/orphHCA/OrphHCA.py
lib/orphHCA/SegHCA.py
lib/orphHCA/__init__.py
lib/orphHCA/filteringOrphHCA.py
lib/orphHCA/orphhca_annotation.py
lib/orphHCA/orphhca_hmm.py
lib/orphHCA/orphhca_io.py
lib/orphHCA/orphhca_sequence.py
lib/orphHCA/orphhca_util.py
orphHCA.egg-info/PKG-INFO
orphHCA.egg-info/SOURCES.txt
orphHCA.egg-info/dependency_links.txt
orphHCA.egg-info/top_level.txt
scripts/filterOrphHCA
scripts/filterOrphHCA.bat
scripts/orphHCA
scripts/orphHCA.bat