Metadata-Version: 1.1
Name: orphHCA
Version: 0.5
Summary: Combined Pfam and HCA ananlysis to improve domain annotation
Home-page: http://www.bornberglab.org/
Author: Tristan Bitard-Feildel
Author-email: t.bitard.feildel@uni-muenster.de
License: GPL
Keywords: protein,domain,HCA,evolution,
Platform: UNKNOWN
Classifier: Development Status :: 5 - Production/Stable
Classifier: Intended Audience :: Science/Research
Classifier: Operating System :: MacOS
Classifier: Operating System :: POSIX
Classifier: Programming Language :: Python
Classifier: Programming Language :: Python :: 2
Classifier: Topic :: Scientific/Engineering :: Bio-Informatics
Provides: orphHCA (0.5)
